ablkit/__init__.py
ablkit/bridge/__init__.py
ablkit/bridge/base_bridge.py
ablkit/bridge/simple_bridge.py
ablkit/data/__init__.py
ablkit/data/evaluation/__init__.py
ablkit/data/evaluation/base_metric.py
ablkit/data/evaluation/reasoning_metric.py
ablkit/data/evaluation/symbol_accuracy.py
ablkit/data/structures/__init__.py
ablkit/data/structures/base_data_element.py
ablkit/data/structures/list_data.py
ablkit/learning/__init__.py
ablkit/learning/abl_model.py
ablkit/learning/basic_nn.py
ablkit/learning/torch_dataset/__init__.py
ablkit/learning/torch_dataset/classification_dataset.py
ablkit/learning/torch_dataset/prediction_dataset.py
ablkit/learning/torch_dataset/regression_dataset.py
ablkit/reasoning/__init__.py
ablkit/reasoning/kb.py
ablkit/reasoning/reasoner.py
ablkit/utils/__init__.py
ablkit/utils/cache.py
ablkit/utils/logger.py
ablkit/utils/manager.py
ablkit/utils/utils.py
ablkit-0.2.2.dist-info/LICENSE
ablkit-0.2.2.dist-info/METADATA
ablkit-0.2.2.dist-info/WHEEL
ablkit-0.2.2.dist-info/top_level.txt
ablkit-0.2.2.dist-info/RECORD
