Metadata-Version: 2.1
Name: ablkit
Version: 0.2.2
Summary: Abductive Learning (ABL) toolkit
Author-email: LAMDA 2024 <abductivelearning@gmail.com>
License: MIT LICENSE
Project-URL: Homepage, https://github.com/AbductiveLearning/ABLkit
Project-URL: Issues, https://github.com/AbductiveLearning/ABLkit/issues
Keywords: machine-learning,framework,abductive-learning,neuro-symbolic
Classifier: Development Status :: 5 - Production/Stable
Classifier: Intended Audience :: Science/Research
Classifier: Intended Audience :: Developers
Classifier: License :: OSI Approved :: MIT License
Classifier: Programming Language :: Python
Classifier: Topic :: Scientific/Engineering :: Artificial Intelligence
Classifier: Topic :: Software Development
Classifier: Operating System :: POSIX :: Linux
Classifier: Operating System :: Microsoft :: Windows
Classifier: Operating System :: MacOS :: MacOS X
Classifier: Programming Language :: Python :: 3.7
Classifier: Programming Language :: Python :: 3.8
Classifier: Programming Language :: Python :: 3.9
Classifier: Programming Language :: Python :: 3.10
Classifier: Programming Language :: Python :: 3.11
Requires-Python: >=3.7.0
License-File: LICENSE
Requires-Dist: numpy >=1.15.0
Requires-Dist: pyswip ==0.2.9
Requires-Dist: torch >=1.11.0
Requires-Dist: torchvision >=0.12.0
Requires-Dist: zoopt >=0.3.0
Requires-Dist: termcolor >=2.3.0
Provides-Extra: test
Requires-Dist: pytest-cov ; extra == 'test'
Requires-Dist: black ==22.10.0 ; extra == 'test'
